{"cameraMode":{"drawMode":0,"name":"Shaded","section":"Shading Mode"},"sceneLighting":true,"audioPlay":false,"sceneViewState":{"showFog":false,"showMaterialUpdate":false,"showSkybox":true,"showFlares":true,"showImageEffects":true,"showParticleSystems":true,"showVisualEffectGraphs":true,"m_FxEnabled":true},"in2DMode":false,"pivot":{"x":-3.15708589553833,"y":1.0289416313171387,"z":-0.8040835857391357},"rotation":{"x":-0.002120050135999918,"y":0.9969882369041443,"z":-0.07375206053256989,"w":-0.040484555065631869},"size":10.0,"orthographic":false}